lunary/__init__.py
lunary/agent.py
lunary/anthropic_utils.py
lunary/config.py
lunary/consumer.py
lunary/event_queue.py
lunary/exceptions.py
lunary/ibm_utils.py
lunary/openai_utils.py
lunary/parent.py
lunary/parsers.py
lunary/project.py
lunary/py.typed
lunary/run_manager.py
lunary/tags.py
lunary/thread.py
lunary/users.py
lunary/utils.py
lunary-1.4.35.dist-info/METADATA
lunary-1.4.35.dist-info/WHEEL
lunary-1.4.35.dist-info/RECORD
