Metadata-Version: 2.4
Name: lunary
Version: 1.4.35
Summary: Python SDK for Lunary, the open-source platform where GenAI teams manage and improve LLM chatbots.
Keywords: Lunary,lunary.ai,Langchain,AI,Analytics,Monitoring,LLM,GenAI,SDK
Author: lunary
Author-email: hello@lunary.ai
Requires-Python: >=3.10.0,<4.0.0
Classifier: Programming Language :: Python :: 3
Classifier: Programming Language :: Python :: 3.10
Classifier: Programming Language :: Python :: 3.11
Classifier: Programming Language :: Python :: 3.12
Classifier: Programming Language :: Python :: 3.13
Classifier: Programming Language :: Python :: 3.14
Requires-Dist: aiohttp (>=3.11.11,<4.0.0)
Requires-Dist: chevron (>=0.14.0,<0.15.0)
Requires-Dist: jsonpickle (>=3.0.4,<4.0.0)
Requires-Dist: langchain-community (>=0.3.29,<0.4.0)
Requires-Dist: packaging (>=23.2,<24.0)
Requires-Dist: pydantic (>=2.12.5,<3.0.0)
Requires-Dist: pyhumps (>=3.8.0,<4.0.0)
Requires-Dist: requests (>=2.31.0,<3.0.0)
Requires-Dist: setuptools (>=78.1.1)
Requires-Dist: tenacity (>=8.2.3,<9.0.0)
Project-URL: Documentation, https://lunary.ai/docs/py
Project-URL: Homepage, https://lunary.ai/docs/py
Project-URL: Repository, https://github.com/lunary-ai/lunary/tree/main/packages/python-sdk
